colorset/__init__.py
colorset/colorset.py
colorset-1.0.0.dist-info/METADATA
colorset-1.0.0.dist-info/WHEEL
colorset-1.0.0.dist-info/top_level.txt
colorset-1.0.0.dist-info/RECORD
