Metadata-Version: 2.1
Name: colorset
Version: 1.0.0
Summary: Colorset management classes
Home-page: https://github.com/AlexTaran/colorset
Author: AlexTaran
Author-email: at@dmtel.ru
Project-URL: Documentation, https://github.com/AlexTaran/colorset
Keywords: colorset legend python
Classifier: Programming Language :: Python :: 3.10
Classifier: License :: OSI Approved :: MIT License
Classifier: Operating System :: OS Independent
Requires-Python: >=3.10
Requires-Dist: lxml (>=4.9.2)
